ezllm/Client.py
ezllm/Collection.py
ezllm/Collections.py
ezllm/Document.py
ezllm/Documents.py
ezllm/Entity.py
ezllm/Filter.py
ezllm/Retrieval.py
ezllm/Scan.py
ezllm/Search.py
ezllm/SubDoc.py
ezllm/__init__.py
ezllm/helpers.py
ezllm/constants/__init__.py
ezllm/errors/__init__.py
ezllm/methods/Base.py
ezllm/methods/ExtractionMethod.py
ezllm/methods/QAMethod.py
ezllm/methods/__init__.py
ezllm/response/Base.py
ezllm/response/Costs.py
ezllm/response/DocOutputGroup.py
ezllm/response/OutputGroup.py
ezllm/response/ResponseDocs.py
ezllm/response/__init__.py
ezllm/response/methods/ExtractionResponse.py
ezllm/response/methods/QA.py
ezllm/response/methods/__init__.py
ezllm/response/retrieval/Filter.py
ezllm/response/retrieval/Scan.py
ezllm/response/retrieval/Search.py
ezllm/response/retrieval/__init__.py
ezllm/types/__init__.py
tests/__init__.py
tests/constants.py
tests/test_client.py
tests/test_crud.py
tests/test_filter.py
tests/test_instantiate.py
tests/test_method_extraction.py
tests/test_method_qa.py
tests/test_response.py
tests/test_scan.py
tests/test_search.py
tests/test_upload.py
ezllm-0.1.2.dist-info/METADATA
ezllm-0.1.2.dist-info/WHEEL
ezllm-0.1.2.dist-info/top_level.txt
ezllm-0.1.2.dist-info/RECORD
