Metadata-Version: 2.1
Name: ezllm
Version: 0.1.2
Summary: Enhance your data pipelines with the power of Large Language Models. EzLLM is a developer tool that opens the door to the LLM ecosystem. Automatic webscrapers, natural language data extraction, semantic search and as little as 3 lines of code
Home-page: https://github.com/FullPort-dev/ezllm-python
Author: EzLLM
Author-email: info@fullport.dev
License: MIT
Project-URL: Homepage, https://ezllm.io
Project-URL: Documentation, https://docs.ezllm.io
Project-URL: Source, https://github.com/FullPort-dev/ezllm-python
Project-URL: Tracker, https://github.com/FullPort-dev/ezllm-python/issues
Project-URL: Developer Console, https://console.ezllm.io
Classifier: Programming Language :: Python :: 3
Classifier: License :: OSI Approved :: MIT License
Classifier: Operating System :: OS Independent
Requires-Dist: requests
Requires-Dist: python-dotenv
Requires-Dist: pydantic
Provides-Extra: extra
Requires-Dist: pandas ; extra == 'extra'
